<annotation><folder>JPEGImages</folder><filename>IndiaVSOman281.jpg</filename><size><width>320</width><height>320</height><depth>3</depth></size><object><name>9</name><difficult>0</difficult><keypoints><x1>74</x1><y1>91</y1><v1>2</v1></keypoints><bndbox><xmin>74</xmin><ymin>91</ymin><xmax>74</xmax><ymax>91</ymax></bndbox></object><object><name>8</name><difficult>0</difficult><keypoints><x1>31</x1><y1>110</y1><v1>2</v1></keypoints><bndbox><xmin>31</xmin><ymin>110</ymin><xmax>31</xmax><ymax>110</ymax></bndbox></object><object><name>7</name><difficult>0</difficult><keypoints><x1>105</x1><y1>100</y1><v1>2</v1></keypoints><bndbox><xmin>105</xmin><ymin>100</ymin><xmax>105</xmax><ymax>100</ymax></bndbox></object><object><name>24</name><difficult>0</difficult><keypoints><x1>65</x1><y1>124</y1><v1>2</v1></keypoints><bndbox><xmin>65</xmin><ymin>124</ymin><xmax>65</xmax><ymax>124</ymax></bndbox></object><object><name>23</name><difficult>0</difficult><keypoints><x1>108</x1><y1>143</y1><v1>2</v1></keypoints><bndbox><xmin>108</xmin><ymin>143</ymin><xmax>108</xmax><ymax>143</ymax></bndbox></object><object><name>2</name><difficult>0</difficult><keypoints><x1>164</x1><y1>170</y1><v1>2</v1></keypoints><bndbox><xmin>164</xmin><ymin>170</ymin><xmax>164</xmax><ymax>170</ymax></bndbox></object><object><name>3</name><difficult>0</difficult><keypoints><x1>197</x1><y1>127</y1><v1>2</v1></keypoints><bndbox><xmin>197</xmin><ymin>127</ymin><xmax>197</xmax><ymax>127</ymax></bndbox></object><object><name>4</name><difficult>0</difficult><keypoints><x1>174</x1><y1>136</y1><v1>2</v1></keypoints><bndbox><xmin>174</xmin><ymin>136</ymin><xmax>174</xmax><ymax>136</ymax></bndbox></object><object><name>6</name><difficult>0</difficult><keypoints><x1>113</x1><y1>113</y1><v1>2</v1></keypoints><bndbox><xmin>113</xmin><ymin>113</ymin><xmax>113</xmax><ymax>113</ymax></bndbox></object><object><name>5</name><difficult>0</difficult><keypoints><x1>133</x1><y1>108</y1><v1>2</v1></keypoints><bndbox><xmin>133</xmin><ymin>108</ymin><xmax>133</xmax><ymax>108</ymax></bndbox></object><object><name>1</name><difficult>0</difficult><keypoints><x1>251</x1><y1>145</y1><v1>2</v1></keypoints><bndbox><xmin>251</xmin><ymin>145</ymin><xmax>251</xmax><ymax>145</ymax></bndbox></object></annotation>